[
  {
    "model": "LSTM",
    "dataset": "FD001",
    "RMSE": 13.7376,
    "NASA_Score": 266.66
  },
  {
    "model": "LSTM",
    "dataset": "FD002",
    "RMSE": 17.0199,
    "NASA_Score": 1701.13
  },
  {
    "model": "LSTM",
    "dataset": "FD003",
    "RMSE": 15.1525,
    "NASA_Score": 858.44
  },
  {
    "model": "LSTM",
    "dataset": "FD004",
    "RMSE": 29.4169,
    "NASA_Score": 60132.26
  },
  {
    "model": "LSTM_W10",
    "dataset": "FD001",
    "RMSE": 41.1287,
    "NASA_Score": 24611.13
  },
  {
    "model": "LSTM_W10",
    "dataset": "FD002",
    "RMSE": 44.3525,
    "NASA_Score": 94016.92
  },
  {
    "model": "LSTM_W10",
    "dataset": "FD003",
    "RMSE": 42.9517,
    "NASA_Score": 48484.53
  },
  {
    "model": "LSTM_W10",
    "dataset": "FD004",
    "RMSE": 45.0881,
    "NASA_Score": 141903.41
  },
  {
    "model": "LSTM_W20",
    "dataset": "FD001",
    "RMSE": 20.1175,
    "NASA_Score": 2028.24
  },
  {
    "model": "LSTM_W20",
    "dataset": "FD002",
    "RMSE": 43.8715,
    "NASA_Score": 76682.42
  },
  {
    "model": "LSTM_W20",
    "dataset": "FD003",
    "RMSE": 20.201,
    "NASA_Score": 1079.29
  },
  {
    "model": "LSTM_W20",
    "dataset": "FD004",
    "RMSE": 44.2254,
    "NASA_Score": 103525.66
  },
  {
    "model": "LSTM_W50",
    "dataset": "FD001",
    "RMSE": 19.7269,
    "NASA_Score": 875.37
  },
  {
    "model": "LSTM_W50",
    "dataset": "FD002",
    "RMSE": 42.9629,
    "NASA_Score": 38401.98
  },
  {
    "model": "LSTM_W50",
    "dataset": "FD003",
    "RMSE": 17.5419,
    "NASA_Score": 604.58
  },
  {
    "model": "LSTM_W50",
    "dataset": "FD004",
    "RMSE": 43.3913,
    "NASA_Score": 67246.05
  },
  {
    "model": "CNN",
    "dataset": "FD001",
    "RMSE": 19.3271,
    "NASA_Score": 1144.31
  },
  {
    "model": "CNN",
    "dataset": "FD002",
    "RMSE": 19.549,
    "NASA_Score": 2606.17
  },
  {
    "model": "CNN",
    "dataset": "FD003",
    "RMSE": 23.3021,
    "NASA_Score": 3219.73
  },
  {
    "model": "CNN",
    "dataset": "FD004",
    "RMSE": 22.0744,
    "NASA_Score": 4916.58
  },
  {
    "model": "LSTM_W30",
    "dataset": "FD001",
    "RMSE": 15.9572,
    "NASA_Score": 317.37
  },
  {
    "model": "LSTM_W30",
    "dataset": "FD002",
    "RMSE": 43.4512,
    "NASA_Score": 61384.65
  },
  {
    "model": "LSTM_W30",
    "dataset": "FD003",
    "RMSE": 40.5147,
    "NASA_Score": 23799.11
  },
  {
    "model": "LSTM_W30",
    "dataset": "FD004",
    "RMSE": 43.9912,
    "NASA_Score": 93496.32
  },
  {
    "model": "RF",
    "dataset": "FD001",
    "RMSE": 16.8001,
    "NASA_Score": 712.76
  },
  {
    "model": "RF",
    "dataset": "FD002",
    "RMSE": 18.2231,
    "NASA_Score": 1661.69
  },
  {
    "model": "RF",
    "dataset": "FD003",
    "RMSE": 17.1068,
    "NASA_Score": 899.1
  },
  {
    "model": "RF",
    "dataset": "FD004",
    "RMSE": 20.5914,
    "NASA_Score": 2864.25
  },
  {
    "model": "Ridge",
    "dataset": "FD001",
    "RMSE": 14.7371,
    "NASA_Score": 373.08
  },
  {
    "model": "Ridge",
    "dataset": "FD002",
    "RMSE": 24.8245,
    "NASA_Score": 81340.16
  },
  {
    "model": "Ridge",
    "dataset": "FD003",
    "RMSE": 16.3135,
    "NASA_Score": 493.23
  },
  {
    "model": "Ridge",
    "dataset": "FD004",
    "RMSE": 32.7817,
    "NASA_Score": 160841.62
  },
  {
    "model": "E2E_Ridge",
    "dataset": "FD001",
    "RMSE": 14.7371,
    "MAE": 11.9519,
    "R2": 0.8648,
    "NASA_Score": 373.08,
    "inference_ms": 0.5106,
    "n_params": 511
  },
  {
    "model": "E2E_RF",
    "dataset": "FD001",
    "RMSE": 16.8001,
    "MAE": 12.575,
    "R2": 0.8242,
    "NASA_Score": 712.76,
    "inference_ms": 52.3776,
    "n_params": 1091238,
    "performance_density": -0.018905
  },
  {
    "model": "E2E_LSTM",
    "dataset": "FD001",
    "RMSE": 15.9572,
    "MAE": 12.5939,
    "R2": 0.8414,
    "NASA_Score": 317.37,
    "inference_ms": 1.9106,
    "n_params": 21313,
    "performance_density": -0.572432
  },
  {
    "model": "E2E_CNN",
    "dataset": "FD001",
    "RMSE": 19.3271,
    "MAE": 14.4844,
    "R2": 0.7674,
    "NASA_Score": 1144.31,
    "inference_ms": 0.7765,
    "n_params": 28545,
    "performance_density": -1.607967
  },
  {
    "model": "E2E_Ensemble",
    "dataset": "FD001",
    "RMSE": 14.8401,
    "MAE": 11.5792,
    "R2": 0.8629,
    "NASA_Score": 371.03,
    "inference_ms": 55.5752
  }
]